LICENSE
pencode/__init__.py
pencode/Logger.py
pencode/pencode.py
README.md
pencode-0.1.2.dist-info/entry_points.txt
pencode-0.1.2.dist-info/LICENSE
pencode-0.1.2.dist-info/WHEEL
pencode-0.1.2.dist-info/METADATA
pencode-0.1.2.dist-info/RECORD
